seo_mcp/__init__.py
seo_mcp/backlinks.py
seo_mcp/keywords.py
seo_mcp/logger.py
seo_mcp/server.py
seo_mcp/traffic.py
seo_mcp_fastmcp-0.2.5.dist-info/METADATA
seo_mcp_fastmcp-0.2.5.dist-info/WHEEL
seo_mcp_fastmcp-0.2.5.dist-info/entry_points.txt
seo_mcp_fastmcp-0.2.5.dist-info/licenses/LICENSE
seo_mcp_fastmcp-0.2.5.dist-info/RECORD
